poketerm-1.0.1.dist-info/licenses/LICENSE
src/__init__.py
src/__main__.py
src/main.py
src/one_liners.py
src/pokemons.py
src/poketermconfig.ini
src/poketermconfig.ini.default
poketerm-1.0.1.dist-info/METADATA
poketerm-1.0.1.dist-info/WHEEL
poketerm-1.0.1.dist-info/entry_points.txt
poketerm-1.0.1.dist-info/top_level.txt
poketerm-1.0.1.dist-info/RECORD
