Metadata-Version: 2.4
Name: poketerm
Version: 1.0.1
Summary: Custom terminal welcome messages, pokemon ASCII art, and random one-liner!
Home-page: https://github.com/devarshi16/TerminalWelcome
Author: devarshi16
Author-email: devarshi16 <devershigpt6@gmail.com>
Requires-Python: >=3.7
License-File: LICENSE
Requires-Dist: readchar>=2.0.1
Requires-Dist: termcolor>=1.1.0
Dynamic: author
Dynamic: home-page
Dynamic: license-file
Dynamic: requires-python
